setup.py
statix_probability/Binomialdistribution.py
statix_probability/Gaussiandistribution.py
statix_probability/Generaldistribution.py
statix_probability/__init__.py
statix_probability.egg-info/PKG-INFO
statix_probability.egg-info/SOURCES.txt
statix_probability.egg-info/dependency_links.txt
statix_probability.egg-info/not-zip-safe
statix_probability.egg-info/top_level.txt