Metadata-Version: 1.0
Name: statix-probability
Version: 0.1
Summary: Gaussian & Binomial distributions
Home-page: UNKNOWN
Author: Subhan Ali
Author-email: subhanali.softengg@gmail.com
License: UNKNOWN
Platform: UNKNOWN
